examples/__init__.py
examples/echobot/__init__.py
examples/echobot/echobot.py
examples/echobot/fixtures.py
examples/echobot/pytest_echobot.py
examples/filebot/__init__.py
examples/filebot/filebot.py
examples/filebot/fixtures.py
examples/filebot/pytest_filebot.py
telegram_bot_unittest/__init__.py
telegram_bot_unittest/core.py
telegram_bot_unittest/fixtures.py
telegram_bot_unittest/routes.py
telegram_bot_unittest/storage.py
telegram_bot_unittest/user.py
telegram_bot_unittest/pytest/__init__.py
telegram_bot_unittest/pytest/fixtures.py
telegram_bot_unittest/pytest/test_bot.py
telegram_bot_unittest/pytest/testbot.py
telegram_bot_unittest-0.4.dist-info/METADATA
telegram_bot_unittest-0.4.dist-info/WHEEL
telegram_bot_unittest-0.4.dist-info/top_level.txt
telegram_bot_unittest-0.4.dist-info/RECORD
