Metadata-Version: 2.1
Name: telegram-bot-unittest
Version: 0.4
Summary: test your python-telegram-bot easily
Home-page: https://github.com/dontsovcmc/telegram_bot_unittest
Author: Dontsov E.
Author-email: dontsovcmc@gmail.com
License: LGPLv3
Platform: UNKNOWN
Classifier: Development Status :: 5 - Production/Stable
Classifier: Intended Audience :: Developers
Classifier: License :: OSI Approved :: GNU Lesser General Public License v3 (LGPLv3)
Classifier: Operating System :: OS Independent
Classifier: Topic :: Software Development :: Libraries :: Python Modules
Classifier: Topic :: Communications :: Chat
Classifier: Topic :: Internet
Classifier: Programming Language :: Python
Classifier: Programming Language :: Python :: 3
Classifier: Programming Language :: Python :: 3.6
Classifier: Programming Language :: Python :: 3.7
Classifier: Programming Language :: Python :: 3.8
Classifier: Programming Language :: Python :: 3.9
Requires-Python: >=3.6
Requires-Dist: python-telegram-bot
Requires-Dist: pytest
Requires-Dist: pytest-cov
Requires-Dist: flask
Requires-Dist: waitress
